{
  "name": "tModLoader (Terraria)",
  "slug": "tmodloader",
  "author": "ops@refx.example",
  "description": "Terraria with mod support. SteamCMD-installed tModLoader dedicated server with workshop modpacks.",
  "category": "modded",
  "deployMethods": [
    "DOCKER",
    "NATIVE_PROCESS"
  ],
  "supportsLinux": true,
  "supportsWindows": false,
  "dockerImages": {
    "Default": "ghcr.io/parkervcp/steamcmd:debian"
  },
  "steamAppId": 1281930,
  "startupCommand": "./start-tModLoaderServer.sh -nosteam -config serverconfig.txt",
  "startupDetect": "Server started",
  "stopCommand": "exit",
  "installScript": {
    "container": "ghcr.io/parkervcp/steamcmd:debian",
    "entrypoint": "bash",
    "script": "#!/bin/bash\n# ReFx steamcmd shim — the steamcmd:debian/proton install image ships no\n# `steamcmd` on PATH. Bootstrap SteamCMD and expose it on PATH so the egg's\n# `steamcmd ...` calls resolve (otherwise the game server never downloads).\nif ! command -v steamcmd >/dev/null 2>&1; then\n  mkdir -p /mnt/server/steamcmd\n  curl -sSL https://steamcdn-a.akamaihd.net/client/installer/steamcmd_linux.tar.gz | tar zxf - -C /mnt/server/steamcmd || { echo \"ERROR: failed to fetch steamcmd\"; exit 1; }\n  chmod +x /mnt/server/steamcmd/steamcmd.sh /mnt/server/steamcmd/linux32/steamcmd 2>/dev/null || true\n  printf '#!/bin/sh\\nexec /mnt/server/steamcmd/steamcmd.sh \"$@\"\\n' > /usr/local/bin/steamcmd\n  chmod +x /usr/local/bin/steamcmd\nfi\nset -euo pipefail\nmkdir -p /mnt/server\ncd /mnt/server\nsteamcmd +force_install_dir /mnt/server +login anonymous +app_update 1281930 validate +quit\nchmod +x start-tModLoaderServer.sh || true\n# Seed tModLoader serverconfig.txt from panel vars (referenced via -config).\nTCFG=/mnt/server/serverconfig.txt\nif [ ! -f \"$TCFG\" ]; then\n  WORLDDIR=/mnt/server/.local/share/Terraria/tModLoader/Worlds\n  mkdir -p \"$WORLDDIR\"\n  {\n    echo \"maxplayers=${MAX_PLAYERS}\"\n    echo \"autocreate=${AUTOCREATE}\"\n    echo \"worldname=${WORLD_NAME}\"\n    echo \"world=${WORLDDIR}/${WORLD_NAME}.wld\"\n    echo \"worldpath=${WORLDDIR}\"\n    [ -n \"${SERVER_PASSWORD}\" ] && echo \"password=${SERVER_PASSWORD}\"\n  } > \"$TCFG\"\nfi\necho 'tModLoader install complete.'\n"
  },
  "configFiles": [],
  "recCpuCores": 2,
  "recMemoryMb": 3072,
  "recDiskMb": 5120,
  "variables": [
    {
      "envName": "WORLD_NAME",
      "displayName": "World Name",
      "description": "Name of the world file to load or create.",
      "type": "STRING",
      "defaultValue": "world",
      "rules": {
        "required": true,
        "maxLength": 64
      },
      "userEditable": true,
      "userViewable": true,
      "sortOrder": 0
    },
    {
      "envName": "MAX_PLAYERS",
      "displayName": "Max Players",
      "description": "Maximum concurrent player slots.",
      "type": "NUMBER",
      "defaultValue": "8",
      "rules": {
        "required": true,
        "min": 1,
        "max": 255
      },
      "userEditable": true,
      "userViewable": true,
      "sortOrder": 1
    },
    {
      "envName": "AUTOCREATE",
      "displayName": "World Size",
      "description": "Size used when auto-creating a new world: 1 small, 2 medium, 3 large.",
      "type": "ENUM",
      "defaultValue": "2",
      "rules": {
        "required": true,
        "options": [
          "1",
          "2",
          "3"
        ]
      },
      "userEditable": true,
      "userViewable": true,
      "sortOrder": 2
    },
    {
      "envName": "SERVER_PASSWORD",
      "displayName": "Server Password",
      "description": "Leave blank for an open server.",
      "type": "SECRET",
      "defaultValue": "",
      "rules": {
        "maxLength": 64
      },
      "userEditable": true,
      "userViewable": false,
      "sortOrder": 3
    }
  ],
  "tags": [
    "sandbox",
    "modded",
    "co-op",
    "multiplayer"
  ],
  "longDescription": "Run modded Terraria with tModLoader and Steam Workshop modpacks on a dedicated server."
}
